setup.py
foko_probability/Binomialdistribution.py
foko_probability/Gaussiandistribution.py
foko_probability/Generaldistribution.py
foko_probability/__init__.py
foko_probability.egg-info/PKG-INFO
foko_probability.egg-info/SOURCES.txt
foko_probability.egg-info/dependency_links.txt
foko_probability.egg-info/not-zip-safe
foko_probability.egg-info/top_level.txt