Metadata-Version: 1.0
Name: foko-probability
Version: 1.0
Summary: Probability distributions
Home-page: UNKNOWN
Author: Foko Valdes
Author-email: research.ciffer@gmail.com
License: UNKNOWN
Platform: UNKNOWN
